babylogger/__init__.py
babylogger-0.1.7.dist-info/METADATA
babylogger-0.1.7.dist-info/WHEEL
babylogger-0.1.7.dist-info/top_level.txt
babylogger-0.1.7.dist-info/RECORD
